core/__init__.py
core/auxiliares/__init__.py
core/auxiliares/auxiliares.py
core/cap1/__init__.py
core/cap1/cifras.py
core/cap1/medidas_del_error.py
core/cap2/__init__.py
core/cap2/separacion_raices.py
core/cap2/resolucion_ecuaciones_algebraicas/__init__.py
core/cap2/resolucion_ecuaciones_algebraicas/biseccion.py
core/cap2/resolucion_ecuaciones_algebraicas/newton_raphson.py
core/cap2/resolucion_ecuaciones_algebraicas/regula_falsi.py
core/cap2/resolucion_ecuaciones_algebraicas/secantes.py
core/cap3/__init__.py
core/cap3/metodos/__init__.py
core/cap3/metodos/gauss_seidel.py
core/cap3/metodos/jacobi.py
core/cap3/utilidades/__init__.py
core/cap3/utilidades/convertir_matriz.py
core/cap3/utilidades/diagonal_predominante.py
core/cap3/utilidades/factor_convergencia.py
core/cap4/__init__.py
core/cap4/lagrange.py
core/cap4/newton_diff.py
core/cap5/__init__.py
core/cap6/__init__.py
core/cap7/__init__.py
mn_api-0.6.1.dist-info/LICENSE
mn_api-0.6.1.dist-info/METADATA
mn_api-0.6.1.dist-info/WHEEL
mn_api-0.6.1.dist-info/top_level.txt
mn_api-0.6.1.dist-info/RECORD
