Metadata-Version: 2.1
Name: mn-api
Version: 0.6.1
Summary: Big sort of numerical methods. Code and docs are in spanish ;)
Home-page: https://github.com/EduardoProfe666/mn-api
Author: EduardoProfe66
Author-email: eduardoglez64377@gmail.com
Keywords: numerical methods,metodos numericos,cujae,python,jupyter-lab
Classifier: Development Status :: 1 - Planning
Classifier: Intended Audience :: Developers
Classifier: Programming Language :: Python :: 3
Classifier: Operating System :: Unix
Classifier: Operating System :: MacOS :: MacOS X
Classifier: Operating System :: Microsoft :: Windows
Requires-Python: >=3.9, <4
License-File: LICENSE
Requires-Dist: numpy
Requires-Dist: scipy
Requires-Dist: simpy
Requires-Dist: sympy
Requires-Dist: pandas
Requires-Dist: tabulate
